microtranslator/__init__.py
microtranslator/translator.py
MicroTranslator-1.0.3.dist-info/LICENSE
MicroTranslator-1.0.3.dist-info/METADATA
MicroTranslator-1.0.3.dist-info/WHEEL
MicroTranslator-1.0.3.dist-info/top_level.txt
MicroTranslator-1.0.3.dist-info/RECORD
