Metadata-Version: 2.1
Name: MicroTranslator
Version: 1.0.3
Summary: A lightweight, simple to use wrapper for the Microsoft translate API.
Home-page: https://github.com/OliMations/MicroTranslator
Author: OliMations
Author-email: support@jakebot.co.uk
License: UNKNOWN
Project-URL: Bug Tracker, https://github.com/OliMations/MicroTranslator/issues
Platform: UNKNOWN
Classifier: Programming Language :: Python :: 3
Classifier: License :: OSI Approved :: MIT License
Classifier: Operating System :: OS Independent
Requires-Python: >=3.6
